.travis.yml
CHANGES.rst
LICENSE
MANIFEST.in
Makefile
README.rst
setup.cfg
setup.py
tox.ini
cryptoyaml/.coveragerc
cryptoyaml/__init__.py
cryptoyaml/api.py
cryptoyaml/commands.py
cryptoyaml/testing.py
cryptoyaml.egg-info/PKG-INFO
cryptoyaml.egg-info/SOURCES.txt
cryptoyaml.egg-info/dependency_links.txt
cryptoyaml.egg-info/entry_points.txt
cryptoyaml.egg-info/not-zip-safe
cryptoyaml.egg-info/requires.txt
cryptoyaml.egg-info/top_level.txt
cryptoyaml/tests/conftest.py
cryptoyaml/tests/test_api.py
cryptoyaml/tests/data/plaintext.yml
cryptoyaml/tests/data/secret
cryptoyaml/tests/data/settings.yml.aes
docs/Makefile
docs/conf.py
docs/index.rst